QGrain/__init__.py
QGrain/distributions.py
QGrain/emma.py
QGrain/generate.py
QGrain/kernels.py
QGrain/metrics.py
QGrain/ssu.py
QGrain/statistics.py
QGrain/udm.py
QGrain/utils.py
QGrain/assets/README.md
QGrain/assets/SourceHanSansCN-Bold.ttf
QGrain/assets/SourceHanSansCN-Regular.ttf
QGrain/assets/dark_theme.xml
QGrain/assets/default_theme.xml
QGrain/assets/en.qm
QGrain/assets/icon.png
QGrain/assets/light_theme.xml
QGrain/assets/manual.pdf
QGrain/assets/zh_CN.qm
QGrain/charts/BoxplotChart.py
QGrain/charts/CumulativeChart.py
QGrain/charts/DistributionChart.py
QGrain/charts/EMMAResultChart.py
QGrain/charts/Frequency3DChart.py
QGrain/charts/FrequencyChart.py
QGrain/charts/FrequencyGroupChart.py
QGrain/charts/FrequencyHeatmap.py
QGrain/charts/HierarchicalChart.py
QGrain/charts/LossSeriesChart.py
QGrain/charts/PCAResultChart.py
QGrain/charts/UDMResultChart.py
QGrain/charts/__init__.py
QGrain/charts/diagrams.py
QGrain/io/__init__.py
QGrain/io/load.py
QGrain/io/save.py
QGrain/models/__init__.py
QGrain/models/artificial_dataset.py
QGrain/models/dataset.py
QGrain/models/emma_result.py
QGrain/models/ssu_result.py
QGrain/models/udm_result.py
QGrain/protos/__init__.py
QGrain/protos/client.py
QGrain/protos/qgrain_pb2.py
QGrain/protos/qgrain_pb2_grpc.py
QGrain/protos/server.py
QGrain/ui/About.py
QGrain/ui/ClusteringAnalyzer.py
QGrain/ui/DatasetGenerator.py
QGrain/ui/DatasetLoader.py
QGrain/ui/EMMAAnalyzer.py
QGrain/ui/EMMASettings.py
QGrain/ui/MainWindow.py
QGrain/ui/PCAAnalyzer.py
QGrain/ui/ParameterEditor.py
QGrain/ui/ParameterTable.py
QGrain/ui/RuntimeLog.py
QGrain/ui/SSUAnalyzer.py
QGrain/ui/SSUMulticoreAnalyzer.py
QGrain/ui/SSUResultViewer.py
QGrain/ui/SSUSettings.py
QGrain/ui/StatisticalAnalyzer.py
QGrain/ui/UDMAnalyzer.py
QGrain/ui/UDMSettings.py
QGrain/ui/__init__.py
QGrain-0.5.4.1.dist-info/LICENSE
QGrain-0.5.4.1.dist-info/LICENSE.rtf
QGrain-0.5.4.1.dist-info/METADATA
QGrain-0.5.4.1.dist-info/WHEEL
QGrain-0.5.4.1.dist-info/entry_points.txt
QGrain-0.5.4.1.dist-info/top_level.txt
QGrain-0.5.4.1.dist-info/RECORD
