Metadata-Version: 2.1
Name: QGrain
Version: 0.5.4.1
Summary: An easy-to-use software for the comprehensive analysis of grain size distributions
Home-page: https://github.com/yuriok/QGrain
Author: Yuming Liu
Author-email: liuyuming@ieecas.cn
License: MIT
Platform: all
Classifier: Programming Language :: Python :: 3
Classifier: License :: OSI Approved :: MIT License
Classifier: Operating System :: OS Independent
Classifier: Intended Audience :: Science/Research
Classifier: Topic :: Scientific/Engineering
Classifier: Topic :: Software Development
Classifier: Natural Language :: Chinese (Simplified)
Classifier: Natural Language :: English
License-File: LICENSE
License-File: LICENSE.rtf
Requires-Dist: psutil
Requires-Dist: numpy
Requires-Dist: scipy
Requires-Dist: scikit-learn
Requires-Dist: grpcio
Requires-Dist: protobuf
Requires-Dist: xlrd
Requires-Dist: openpyxl
Requires-Dist: PySide6 (>=6.2.0)
Requires-Dist: matplotlib (>=3.5.0)
Requires-Dist: SciencePlots
Requires-Dist: qt-material
Provides-Extra: server
Requires-Dist: torch ; extra == 'server'
